oakx_oger/__init__.py
oakx_oger/cli.py
oakx_oger/input/README.md
oakx_oger/input/tmp/README.md
oakx_oger/oger_implementation.py
oakx_oger/stopwords/stopwords.txt
oakx_oger-0.1.6.dist-info/LICENSE
oakx_oger-0.1.6.dist-info/METADATA
oakx_oger-0.1.6.dist-info/WHEEL
oakx_oger-0.1.6.dist-info/entry_points.txt
oakx_oger-0.1.6.dist-info/RECORD
