Metadata-Version: 2.1
Name: oakx-oger
Version: 0.1.6
Summary: OGER plugin for oaklib
Author: Harshad Hegde
Author-email: hhegde@lbl.gov
Requires-Python: >=3.9,<4.0
Classifier: Programming Language :: Python :: 3
Classifier: Programming Language :: Python :: 3.9
Classifier: Programming Language :: Python :: 3.10
Classifier: Programming Language :: Python :: 3.11
Provides-Extra: docs
Requires-Dist: OGER (>=1.5,<2.0)
Requires-Dist: click (>=8.1.7,<9.0.0)
Requires-Dist: importlib (>=1.0.4,<2.0.0)
Requires-Dist: oaklib (>=0.5.19)
